HISTORY.rst
LICENSE
MANIFEST.in
README.rst
setup.py
django_respite.egg-info/PKG-INFO
django_respite.egg-info/SOURCES.txt
django_respite.egg-info/dependency_links.txt
django_respite.egg-info/top_level.txt
respite/__init__.py
respite/__init__.pyc
respite/decorators.py
respite/decorators.pyc
respite/formats.py
respite/formats.pyc
respite/inflector.py
respite/inflector.pyc
respite/middleware.py
respite/middleware.pyc
respite/settings.py
respite/settings.pyc
respite/utils.pyc
respite/version.py
respite/version.pyc
respite/lib/__init__.py
respite/lib/__init__.pyc
respite/lib/ordereddict.py
respite/locale/nb/LC_MESSAGES/django.mo
respite/locale/nb/LC_MESSAGES/django.po
respite/serializers/__init__.py
respite/serializers/__init__.pyc
respite/serializers/base.py
respite/serializers/base.pyc
respite/serializers/jsonpserializer.py
respite/serializers/jsonpserializer.pyc
respite/serializers/jsonserializer.py
respite/serializers/jsonserializer.pyc
respite/serializers/xmlserializer.py
respite/serializers/xmlserializer.pyc
respite/static/respite/js/jquery.respite.js
respite/urls/__init__.py
respite/urls/__init__.pyc
respite/urls/resource.py
respite/urls/resource.pyc
respite/urls/routes.py
respite/urls/routes.pyc
respite/urls/templates.py
respite/urls/templates.pyc
respite/utils/__init__.py
respite/utils/__init__.pyc
respite/utils/datastructures.py
respite/utils/datastructures.pyc
respite/utils/parsers.py
respite/utils/parsers.pyc
respite/views/__init__.py
respite/views/__init__.pyc
respite/views/resource.py
respite/views/resource.pyc
respite/views/views.py
respite/views/views.pyc