Metadata-Version: 1.0
Name: django-respite
Version: 1.4.0
Summary: Respite conforms Django to Representational State Transfer (REST)
Home-page: http://github.com/jgorset/django-respite
Author: Johannes Gorset
Author-email: jgorset@gmail.com
License: UNKNOWN
Platform: UNKNOWN
